pypostfix/RPN.py
pypostfix/Stack.py
pypostfix/__init__.py
pypostfix-1.0.0.dist-info/LICENSE
pypostfix-1.0.0.dist-info/METADATA
pypostfix-1.0.0.dist-info/WHEEL
pypostfix-1.0.0.dist-info/entry_points.txt
pypostfix-1.0.0.dist-info/top_level.txt
pypostfix-1.0.0.dist-info/RECORD
