Metadata-Version: 2.1
Name: pypostfix
Version: 1.0.0
Summary: A library for manipulating expressions in both infix and postfix notation (Reverse Polish Notation or RPN)
Home-page: https://github.com/Slinky802/pypostfix
Author: Alexandre Poggioli
Author-email: alexandrepoggioli09@gmail.com
Classifier: Programming Language :: Python :: 3
Classifier: License :: OSI Approved :: MIT License
Classifier: Operating System :: OS Independent
Requires-Python: >=3.5
License-File: LICENSE
